{
  "title": "#fy #aynglesteamo",
  "url": "https://www.tiktok.com/@aingles._/video/7067985493937458438",
  "uploader": "aingles._",
  "uploader_id": "6625705024915177478",
  "upload_date": "2022-02-23",
  "duration_seconds": 60,
  "duration_formatted": "01:00",
  "view_count": 12100000,
  "like_count": 1100000,
  "comment_count": 20800,
  "description": "#fy #aynglesteamo",
  "webpage_url": "https://www.tiktok.com/@aingles._/video/7067985493937458438",
  "extractor": "TikTok",
  "video_id": "7067985493937458438",
  "download_date": "2025-07-25T09:59:34.230498",
  "tags": [],
  "notes": "",
  "categories": [],
  "custom_metadata": {}
}